lerobot/__init__.py
lerobot/__version__.py
lerobot/calibrate.py
lerobot/constants.py
lerobot/errors.py
lerobot/find_cameras.py
lerobot/find_port.py
lerobot/record.py
lerobot/replay.py
lerobot/setup_motors.py
lerobot/teleoperate.py
lerobot/cameras/__init__.py
lerobot/cameras/camera.py
lerobot/cameras/configs.py
lerobot/cameras/utils.py
lerobot/cameras/dummy/__init__.py
lerobot/cameras/dummy/camera_dummy.py
lerobot/cameras/dummy/configuration_dummy.py
lerobot/cameras/opencv/__init__.py
lerobot/cameras/opencv/camera_opencv.py
lerobot/cameras/opencv/configuration_opencv.py
lerobot/cameras/realsense/__init__.py
lerobot/cameras/realsense/camera_realsense.py
lerobot/cameras/realsense/configuration_realsense.py
lerobot/configs/default.py
lerobot/configs/eval.py
lerobot/configs/parser.py
lerobot/configs/policies.py
lerobot/configs/train.py
lerobot/configs/types.py
lerobot/datasets/backward_compatibility.py
lerobot/datasets/card_template.md
lerobot/datasets/compute_stats.py
lerobot/datasets/downloader.py
lerobot/datasets/factory.py
lerobot/datasets/image_writer.py
lerobot/datasets/lerobot_dataset.py
lerobot/datasets/online_buffer.py
lerobot/datasets/sampler.py
lerobot/datasets/transforms.py
lerobot/datasets/utils.py
lerobot/datasets/video_utils.py
lerobot/datasets/hubs/abstract_hub.py
lerobot/datasets/hubs/hf_hub.py
lerobot/datasets/hubs/ms_hub.py
lerobot/datasets/push_dataset_to_hub/utils.py
lerobot/datasets/v2/batch_convert_dataset_v1_to_v2.py
lerobot/datasets/v2/convert_dataset_v1_to_v2.py
lerobot/datasets/v21/_remove_language_instruction.py
lerobot/datasets/v21/batch_convert_dataset_v20_to_v21.py
lerobot/datasets/v21/convert_dataset_v20_to_v21.py
lerobot/datasets/v21/convert_stats.py
lerobot/envs/__init__.py
lerobot/envs/configs.py
lerobot/envs/factory.py
lerobot/envs/utils.py
lerobot/model/kinematics.py
lerobot/motors/__init__.py
lerobot/motors/calibration_gui.py
lerobot/motors/motors_bus.py
lerobot/motors/dynamixel/__init__.py
lerobot/motors/dynamixel/dynamixel.py
robocoin-0.1.0.1.dist-info/licenses/LICENSE
robocoin-0.1.0.1.dist-info/METADATA
robocoin-0.1.0.1.dist-info/WHEEL
robocoin-0.1.0.1.dist-info/entry_points.txt
robocoin-0.1.0.1.dist-info/top_level.txt
robocoin-0.1.0.1.dist-info/RECORD
